dev_rewind/__init__.py
dev_rewind/cli/__init__.py
dev_rewind/cli/click/__init__.py
dev_rewind/cli/streamlit/__init__.py
dev_rewind/cli/streamlit/entry.py
dev_rewind/cli/streamlit/ui.py
dev_rewind/config.py
dev_rewind/core/__init__.py
dev_rewind/core/agent/__init__.py
dev_rewind/core/agent/summary.py
dev_rewind/core/agent/tools.py
dev_rewind/core/cache.py
dev_rewind/core/collector/__init__.py
dev_rewind/core/context.py
dev_rewind/core/stopword.py
dev_rewind/exc.py
dev_rewind/test_core.py
devrewind-0.2.0.dist-info/LICENSE
devrewind-0.2.0.dist-info/METADATA
devrewind-0.2.0.dist-info/WHEEL
devrewind-0.2.0.dist-info/entry_points.txt
devrewind-0.2.0.dist-info/RECORD
