Metadata-Version: 2.1
Name: DevRewind
Version: 0.2.0
Summary: 
License: Apache-2.0
Author: williamfzc
Author-email: williamfzc@foxmail.com
Requires-Python: >=3.8, !=2.7.*, !=3.0.*, !=3.1.*, !=3.2.*, !=3.3.*, !=3.4.*, !=3.5.*, !=3.6.*, !=3.7.*
Classifier: License :: OSI Approved :: Apache Software License
Classifier: Programming Language :: Python :: 3
Classifier: Programming Language :: Python :: 3.9
Classifier: Programming Language :: Python :: 3.10
Classifier: Programming Language :: Python :: 3.11
Requires-Dist: chromadb (>=0.4.14,<0.5.0)
Requires-Dist: click (>=8.1.7,<9.0.0)
Requires-Dist: gitpython (>=3.1.38,<4.0.0)
Requires-Dist: jieba (>=0.42.1,<0.43.0)
Requires-Dist: keybert (>=0.8.3,<0.9.0)
Requires-Dist: langchain (>=0.0.315,<0.0.326)
Requires-Dist: loguru (>=0.7.2,<0.8.0)
Requires-Dist: openai (>=0.28.1,<0.29.0)
Requires-Dist: pydantic (>=2.4.2,<3.0.0)
Requires-Dist: pydantic-settings (>=2.0.3,<3.0.0)
Requires-Dist: rapidfuzz (>=3.4.0,<4.0.0)
Requires-Dist: sentence-transformers (>=2.2.2,<3.0.0)
Requires-Dist: streamlit (>=1.27.2,<2.0.0)
Requires-Dist: tiktoken (>=0.5.1,<0.6.0)
Requires-Dist: tinydb (>=4.8.0,<5.0.0)
